sql_extended_objects/__init__.py
sql_extended_objects/sql_extended_objects.py
sql_extended_objects/version
SQLExtendedObjects-1.0.2.dist-info/METADATA
SQLExtendedObjects-1.0.2.dist-info/WHEEL
SQLExtendedObjects-1.0.2.dist-info/top_level.txt
SQLExtendedObjects-1.0.2.dist-info/RECORD
