Metadata-Version: 2.1
Name: SQLExtendedObjects
Version: 1.0.2
Summary: Utilities and Classes for making easier work with SQLite Tables
Home-page: https://github.com/Ar4ikov/SQLExtendedObjects
Author: Nikita Archikov
Author-email: bizy18588@gmail.com
License: MIT License
